README.txt
setup.py
collective/__init__.py
collective.psc.externalstorage.egg-info/PKG-INFO
collective.psc.externalstorage.egg-info/SOURCES.txt
collective.psc.externalstorage.egg-info/dependency_links.txt
collective.psc.externalstorage.egg-info/entry_points.txt
collective.psc.externalstorage.egg-info/namespace_packages.txt
collective.psc.externalstorage.egg-info/not-zip-safe
collective.psc.externalstorage.egg-info/requires.txt
collective.psc.externalstorage.egg-info/top_level.txt
collective/psc/__init__.py
collective/psc/externalstorage/__init__.py
collective/psc/externalstorage/config.py
collective/psc/externalstorage/configure.zcml
collective/psc/externalstorage/interfaces.py
collective/psc/externalstorage/profiles.zcml
collective/psc/externalstorage/browser/__init__.py
collective/psc/externalstorage/browser/config.py
collective/psc/externalstorage/browser/configure.zcml
collective/psc/externalstorage/profiles/default/componentregistry.xml
collective/psc/externalstorage/profiles/default/controlpanel.xml
collective/psc/externalstorage/profiles/default/metadata.xml
collective/psc/externalstorage/tests/__init__.py
collective/psc/externalstorage/tests/configure.zcml
collective/psc/externalstorage/tests/sample.tar.gz
collective/psc/externalstorage/tests/test_config.py
collective/psc/externalstorage/tests/test_lock.py
docs/CONTRIBUTORS.txt
docs/HISTORY.txt