Metadata-Version: 1.0
Name: collective.psc.externalstorage
Version: 0.1.2
Summary: External storage for PloneSoftwareCenter
Home-page: http://svn.plone.org/svn/collective/collective.psc.externalstorage
Author: Tarek Ziade
Author-email: tarek@ziade.org
License: GPL
Keywords: psc disutils storage
Platform: UNKNOWN
Classifier: Programming Language :: Python
Classifier: Topic :: Software Development :: Libraries :: Python Modules
